local_redash/__init__.py
local_redash/command_executer.py
local_redash/commands/base.py
local_redash/commands/data_source_list.py
local_redash/commands/export_query.py
local_redash/commands/query.py
local_redash/commands/query_list.py
local_redash/commands/run_query.py
local_redash/commands/show_query.py
local_redash/config.yml
local_redash/containers.py
local_redash/exceptions.py
local_redash/lib/config_file.py
local_redash/lib/redash_client.py
local_redash/main.py
local_redash/models/redash_client.py
local_redash-0.0.2.dist-info/METADATA
local_redash-0.0.2.dist-info/WHEEL
local_redash-0.0.2.dist-info/entry_points.txt
local_redash-0.0.2.dist-info/RECORD
