Metadata-Version: 2.1
Name: local-redash
Version: 0.0.2
Summary: 
Home-page: https://github.com/myoshioka/local-redash
License: MIT
Keywords: redash,sql
Author: Makoto Yoshioka
Author-email: y.mako2@gmail.com
Requires-Python: >=3.10,<4.0
Classifier: License :: OSI Approved :: MIT License
Classifier: Programming Language :: Python :: 3
Classifier: Programming Language :: Python :: 3.10
Classifier: Programming Language :: Python :: 3.11
Requires-Dist: click (>=8.1.3,<9.0.0)
Requires-Dist: click-option-group (>=0.5.6,<0.6.0)
Requires-Dist: dependency-injector (>=4.41.0,<5.0.0)
Requires-Dist: httpx (>=0.24.0,<0.25.0)
Requires-Dist: pydantic (>=1.10.7,<2.0.0)
Requires-Dist: python-dotenv (>=0.21.0,<0.22.0)
Requires-Dist: pyyaml (>=6.0,<7.0)
Requires-Dist: sqlfluff (>=2.1.1,<3.0.0)
Requires-Dist: tabulate (>=0.8.10,<0.9.0)
Requires-Dist: timeout-decorator (>=0.5.0,<0.6.0)
Requires-Dist: wcwidth (>=0.2.6,<0.3.0)
Project-URL: Repository, https://github.com/myoshioka/local-redash
